[
  {
    "station_id": "station_01",
    "timestamp": "2025-03-26T20:11:13.441073",
    "temperature": -29.91,
    "humidity": 48.73,
    "co2": 879.91
  },
  {
    "station_id": "station_01",
    "timestamp": "2025-03-26T20:11:23.446666",
    "temperature": -17.07,
    "humidity": 99.8,
    "co2": 1342.66
  },
  {
    "station_id": "station_01",
    "timestamp": "2025-03-26T20:11:33.451205",
    "temperature": 6.17,
    "humidity": 97.19,
    "co2": 1591.48
  },
  {
    "station_id": "station_01",
    "timestamp": "2025-03-26T20:11:43.456669",
    "temperature": 0.07,
    "humidity": 45.38,
    "co2": 478.94
  },
  {
    "station_id": "station_01",
    "timestamp": "2025-03-26T20:11:53.457997",
    "temperature": 36.64,
    "humidity": 10.49,
    "co2": 1150.85
  },
  {
    "station_id": "station_01",
    "timestamp": "2025-03-26T20:12:03.460660",
    "temperature": 14.77,
    "humidity": 94.26,
    "co2": 1260.66
  }
]